{
  "version": "6.0",
  "nxVersion": "18.3.4",
  "deps": {
    "@angular/animations": "^17.3.0",
    "@angular/common": "^17.3.0",
    "@angular/compiler": "^17.3.0",
    "@angular/core": "^17.3.0",
    "@angular/forms": "^17.3.0",
    "@angular/platform-browser": "^17.3.0",
    "@angular/platform-browser-dynamic": "^17.3.0",
    "@angular/router": "^17.3.0",
    "@ngrx/effects": "^17.2.0",
    "@ngrx/store": "^17.2.0",
    "normalize.css": "^8.0.1",
    "rxjs": "~7.8.0",
    "tslib": "^2.3.0",
    "zone.js": "~0.14.3",
    "@angular-devkit/build-angular": "^17.3.1",
    "@angular-eslint/builder": "17.3.0",
    "@angular-eslint/eslint-plugin": "17.3.0",
    "@angular-eslint/eslint-plugin-template": "17.3.0",
    "@angular-eslint/schematics": "17.3.0",
    "@angular-eslint/template-parser": "17.3.0",
    "@angular/cli": "^17.3.1",
    "@angular/compiler-cli": "^17.3.0",
    "@ngrx/store-devtools": "^17.2.0",
    "@types/jasmine": "~5.1.0",
    "@typescript-eslint/eslint-plugin": "7.2.0",
    "@typescript-eslint/parser": "7.2.0",
    "eslint": "^8.57.0",
    "eslint-config-prettier": "^9.1.0",
    "eslint-plugin-prettier": "^5.1.3",
    "jasmine-core": "~5.1.0",
    "karma": "~6.4.0",
    "karma-chrome-launcher": "~3.2.0",
    "karma-coverage": "~2.2.0",
    "karma-jasmine": "~5.1.0",
    "karma-jasmine-html-reporter": "~2.1.0",
    "prettier": "3.2.5",
    "prettier-eslint": "^16.3.0",
    "typescript": "~5.4.2"
  },
  "pathMappings": {},
  "nxJsonPlugins": [],
  "fileMap": {
    "nonProjectFiles": [
      {
        "file": "src/app/components/toolbar/toolbar.component.html",
        "hash": "13242240151469699445"
      },
      {
        "file": "src/favicon.ico",
        "hash": "3988961587069885523"
      },
      {
        "file": "src/app/components/canvas/canvas.component.scss",
        "hash": "12389610928147753180"
      },
      {
        "file": "angular.json",
        "hash": "6404970368007684128"
      },
      {
        "file": "src/index.html",
        "hash": "7690192326142999836"
      },
      {
        "file": "src/app/components/canvas/canvas.component.html",
        "hash": "3971738557385275280"
      },
      {
        "file": ".eslintrc",
        "hash": "9017557785506667000"
      },
      {
        "file": "src/app/services/drawing-strategies/circle-drawing-strategy.ts",
        "hash": "11179530008872033602"
      },
      {
        "file": ".gitignore",
        "hash": "17090615579869685144"
      },
      {
        "file": "src/app/services/factory/drawing-strategy-factory.ts",
        "hash": "11504882170056381869"
      },
      {
        "file": "src/app/components/header/header.component.scss",
        "hash": "14698934577211358489"
      },
      {
        "file": "src/app/components/header/header.component.ts",
        "hash": "5677906274831389950"
      },
      {
        "file": "src/app/app.component.spec.ts",
        "hash": "560877037317079384"
      },
      {
        "file": "README.md",
        "hash": "6944952925459130059"
      },
      {
        "file": "src/app/store/selectors.ts",
        "hash": "17208829734659870159"
      },
      {
        "file": "tsconfig.json",
        "hash": "1649115413602447581"
      },
      {
        "file": "package.json",
        "hash": "2829555005584948857"
      },
      {
        "file": "src/assets/icons.svg",
        "hash": "9592228423406364001"
      },
      {
        "file": "src/styles.scss",
        "hash": "5195668842064076916"
      },
      {
        "file": "src/app/components/canvas/canvas.component.ts",
        "hash": "4065060533037579685"
      },
      {
        "file": "src/main.ts",
        "hash": "8060102740304671444"
      },
      {
        "file": "src/app/services/drawing-strategies/line-drawing-strategy.ts",
        "hash": "8539465298917582636"
      },
      {
        "file": "src/app/components/sidebar/sidebar.component.html",
        "hash": "6865211082871867027"
      },
      {
        "file": "src/app/components/toolbar/toolbar.component.ts",
        "hash": "10872894632627781792"
      },
      {
        "file": "package-lock.json",
        "hash": "1307076566974517397"
      },
      {
        "file": "src/app/services/drawing-strategies/drawing-strategy.ts",
        "hash": "14108036059994207838"
      },
      {
        "file": "src/app/components/sidebar/sidebar.component.spec.ts",
        "hash": "908818993137904647"
      },
      {
        "file": "src/app/store/state.ts",
        "hash": "12242579988176243330"
      },
      {
        "file": "src/app/store/actions.ts",
        "hash": "10042023016295106470"
      },
      {
        "file": ".prettierignore",
        "hash": "4394554640825449381"
      },
      {
        "file": ".editorconfig",
        "hash": "6686520031028425313"
      },
      {
        "file": "src/app/components/toolbar/toolbar.component.spec.ts",
        "hash": "17358986880481123933"
      },
      {
        "file": ".vscode/tasks.json",
        "hash": "5336636969995539451"
      },
      {
        "file": "src/app/app.config.ts",
        "hash": "7090238066831601277"
      },
      {
        "file": "src/app/components/toolbar/toolbar.component.scss",
        "hash": "2392238868832091173"
      },
      {
        "file": "src/assets/.gitkeep",
        "hash": "3244421341483603138"
      },
      {
        "file": "src/app/components/header/header.component.spec.ts",
        "hash": "18019974771912921764"
      },
      {
        "file": ".vscode/extensions.json",
        "hash": "5331566439708925252"
      },
      {
        "file": "tsconfig.app.json",
        "hash": "17337579397915052279"
      },
      {
        "file": "src/app/app.component.html",
        "hash": "16521575206848530270"
      },
      {
        "file": "tsconfig.spec.json",
        "hash": "15575553540147145788"
      },
      {
        "file": "src/app/store/reducers.ts",
        "hash": "2378397329758271307"
      },
      {
        "file": "src/app/app.component.ts",
        "hash": "14738164170291893476"
      },
      {
        "file": "src/app/components/sidebar/sidebar.component.ts",
        "hash": "5635981759083114467"
      },
      {
        "file": "src/app/store/facade.ts",
        "hash": "16238450928314897329"
      },
      {
        "file": "src/app/components/canvas/canvas.component.spec.ts",
        "hash": "3646841805231148138"
      },
      {
        "file": ".vscode/launch.json",
        "hash": "17038929134016848735"
      },
      {
        "file": "src/app/app.component.scss",
        "hash": "4943523360744343434"
      },
      {
        "file": "src/app/components/header/header.component.html",
        "hash": "12495740656703924463"
      },
      {
        "file": ".prettierrc",
        "hash": "12381007370531736633"
      },
      {
        "file": "src/app/services/canvas.service.ts",
        "hash": "16143669504862117951"
      },
      {
        "file": "src/app/components/sidebar/sidebar.component.scss",
        "hash": "2857731784493722752"
      },
      {
        "file": "src/app/services/drawing-strategies/rectangle-drawing-strategy.ts",
        "hash": "14392416755130340995"
      }
    ],
    "projectFileMap": {}
  }
}
